{
  "generatedAt": "2026-06-13T06:55:42.979Z",
  "total": 70,
  "schoolMetadata": {
    "fisica": {
      "properSpelling": "Física",
      "EsCatedrado": true,
      "informationBlurb": ""
    },
    "matematica": {
      "properSpelling": "Matemática",
      "EsCatedrado": true,
      "informationBlurb": "La dificultad de los exámenes varía según el año. Hasta el 2019 eran difíciles, durante el 2020 y 2021 fueron fáciles, y a partir del 2022 pasaron a ser moderados."
    }
  },
  "subjectMetadata": {
    "fisica/fisica_1": {
      "properSpelling": "Física 1",
      "courseCode": "FI1101",
      "creditAmount": 3
    },
    "matematica/calculo_diferencial_e_integral": {
      "properSpelling": "Cálculo diferencial e integral",
      "courseCode": "MA1102",
      "creditAmount": 4
    },
    "matematica/calculo_y_algebra_lineal": {
      "properSpelling": "Cálculo y álgebra lineal",
      "courseCode": "MA1103",
      "creditAmount": 4
    },
    "matematica/matematica_discreta": {
      "properSpelling": "Matemática discreta",
      "courseCode": "MA1403",
      "creditAmount": 4
    },
    "matematica/matematica_general": {
      "properSpelling": "Matemática general",
      "courseCode": "MA0101",
      "creditAmount": 2
    }
  },
  "items": [
    {
      "path": "exams/fisica/fisica_1/P1_IIS_2018_E.pdf",
      "school": "fisica",
      "subject": "fisica_1",
      "year": "2018",
      "semester": "IIS",
      "parcial": "P1",
      "kind": "enunciado",
      "kindCode": "E",
      "variant": "regular",
      "variantCode": null,
      "fileName": "P1_IIS_2018_E.pdf",
      "title": "P1 IIS 2018 E"
    },
    {
      "path": "exams/fisica/fisica_1/P1_IS_2026_E_E.pdf",
      "school": "fisica",
      "subject": "fisica_1",
      "year": "2026",
      "semester": "IS",
      "parcial": "P1",
      "kind": "enunciado",
      "kindCode": "E",
      "variant": "extraordinario",
      "variantCode": "E",
      "fileName": "P1_IS_2026_E_E.pdf",
      "title": "P1 IS 2026 E E"
    },
    {
      "path": "exams/fisica/fisica_1/P1_IS_2026_S_E.pdf",
      "school": "fisica",
      "subject": "fisica_1",
      "year": "2026",
      "semester": "IS",
      "parcial": "P1",
      "kind": "solution",
      "kindCode": "S",
      "variant": "extraordinario",
      "variantCode": "E",
      "fileName": "P1_IS_2026_S_E.pdf",
      "title": "P1 IS 2026 S E"
    },
    {
      "path": "exams/fisica/fisica_1/P1_IS_2026_E.pdf",
      "school": "fisica",
      "subject": "fisica_1",
      "year": "2026",
      "semester": "IS",
      "parcial": "P1",
      "kind": "enunciado",
      "kindCode": "E",
      "variant": "regular",
      "variantCode": null,
      "fileName": "P1_IS_2026_E.pdf",
      "title": "P1 IS 2026 E"
    },
    {
      "path": "exams/fisica/fisica_1/P1_IS_2026_S.pdf",
      "school": "fisica",
      "subject": "fisica_1",
      "year": "2026",
      "semester": "IS",
      "parcial": "P1",
      "kind": "solution",
      "kindCode": "S",
      "variant": "regular",
      "variantCode": null,
      "fileName": "P1_IS_2026_S.pdf",
      "title": "P1 IS 2026 S"
    },
    {
      "path": "exams/fisica/fisica_1/P2_IS_2026_E_E.pdf",
      "school": "fisica",
      "subject": "fisica_1",
      "year": "2026",
      "semester": "IS",
      "parcial": "P2",
      "kind": "enunciado",
      "kindCode": "E",
      "variant": "extraordinario",
      "variantCode": "E",
      "fileName": "P2_IS_2026_E_E.pdf",
      "title": "P2 IS 2026 E E"
    },
    {
      "path": "exams/fisica/fisica_1/P2_IS_2026_S_E.pdf",
      "school": "fisica",
      "subject": "fisica_1",
      "year": "2026",
      "semester": "IS",
      "parcial": "P2",
      "kind": "solution",
      "kindCode": "S",
      "variant": "extraordinario",
      "variantCode": "E",
      "fileName": "P2_IS_2026_S_E.pdf",
      "title": "P2 IS 2026 S E"
    },
    {
      "path": "exams/fisica/fisica_1/P2_IS_2026_E.pdf",
      "school": "fisica",
      "subject": "fisica_1",
      "year": "2026",
      "semester": "IS",
      "parcial": "P2",
      "kind": "enunciado",
      "kindCode": "E",
      "variant": "regular",
      "variantCode": null,
      "fileName": "P2_IS_2026_E.pdf",
      "title": "P2 IS 2026 E"
    },
    {
      "path": "exams/fisica/fisica_1/P2_IS_2026_S.pdf",
      "school": "fisica",
      "subject": "fisica_1",
      "year": "2026",
      "semester": "IS",
      "parcial": "P2",
      "kind": "solution",
      "kindCode": "S",
      "variant": "regular",
      "variantCode": null,
      "fileName": "P2_IS_2026_S.pdf",
      "title": "P2 IS 2026 S"
    },
    {
      "path": "exams/matematica/calculo_diferencial_e_integral/P1_IS_2024_E.pdf",
      "school": "matematica",
      "subject": "calculo_diferencial_e_integral",
      "year": "2024",
      "semester": "IS",
      "parcial": "P1",
      "kind": "enunciado",
      "kindCode": "E",
      "variant": "regular",
      "variantCode": null,
      "fileName": "P1_IS_2024_E.pdf",
      "title": "P1 IS 2024 E"
    },
    {
      "path": "exams/matematica/calculo_diferencial_e_integral/P1_IS_2024_S.pdf",
      "school": "matematica",
      "subject": "calculo_diferencial_e_integral",
      "year": "2024",
      "semester": "IS",
      "parcial": "P1",
      "kind": "solution",
      "kindCode": "S",
      "variant": "regular",
      "variantCode": null,
      "fileName": "P1_IS_2024_S.pdf",
      "title": "P1 IS 2024 S"
    },
    {
      "path": "exams/matematica/calculo_diferencial_e_integral/P2_IS_2024_E.pdf",
      "school": "matematica",
      "subject": "calculo_diferencial_e_integral",
      "year": "2024",
      "semester": "IS",
      "parcial": "P2",
      "kind": "enunciado",
      "kindCode": "E",
      "variant": "regular",
      "variantCode": null,
      "fileName": "P2_IS_2024_E.pdf",
      "title": "P2 IS 2024 E"
    },
    {
      "path": "exams/matematica/calculo_diferencial_e_integral/P2_IS_2024_S.pdf",
      "school": "matematica",
      "subject": "calculo_diferencial_e_integral",
      "year": "2024",
      "semester": "IS",
      "parcial": "P2",
      "kind": "solution",
      "kindCode": "S",
      "variant": "regular",
      "variantCode": null,
      "fileName": "P2_IS_2024_S.pdf",
      "title": "P2 IS 2024 S"
    },
    {
      "path": "exams/matematica/calculo_diferencial_e_integral/P3_IS_2024_E.pdf",
      "school": "matematica",
      "subject": "calculo_diferencial_e_integral",
      "year": "2024",
      "semester": "IS",
      "parcial": "P3",
      "kind": "enunciado",
      "kindCode": "E",
      "variant": "regular",
      "variantCode": null,
      "fileName": "P3_IS_2024_E.pdf",
      "title": "P3 IS 2024 E"
    },
    {
      "path": "exams/matematica/calculo_diferencial_e_integral/P3_IS_2024_S.pdf",
      "school": "matematica",
      "subject": "calculo_diferencial_e_integral",
      "year": "2024",
      "semester": "IS",
      "parcial": "P3",
      "kind": "solution",
      "kindCode": "S",
      "variant": "regular",
      "variantCode": null,
      "fileName": "P3_IS_2024_S.pdf",
      "title": "P3 IS 2024 S"
    },
    {
      "path": "exams/matematica/calculo_diferencial_e_integral/RP_IS_2024_E.pdf",
      "school": "matematica",
      "subject": "calculo_diferencial_e_integral",
      "year": "2024",
      "semester": "IS",
      "parcial": "RP",
      "kind": "enunciado",
      "kindCode": "E",
      "variant": "regular",
      "variantCode": null,
      "fileName": "RP_IS_2024_E.pdf",
      "title": "RP IS 2024 E"
    },
    {
      "path": "exams/matematica/calculo_diferencial_e_integral/RP_IS_2024_S.pdf",
      "school": "matematica",
      "subject": "calculo_diferencial_e_integral",
      "year": "2024",
      "semester": "IS",
      "parcial": "RP",
      "kind": "solution",
      "kindCode": "S",
      "variant": "regular",
      "variantCode": null,
      "fileName": "RP_IS_2024_S.pdf",
      "title": "RP IS 2024 S"
    },
    {
      "path": "exams/matematica/calculo_diferencial_e_integral/P1_IIS_2024_E.pdf",
      "school": "matematica",
      "subject": "calculo_diferencial_e_integral",
      "year": "2024",
      "semester": "IIS",
      "parcial": "P1",
      "kind": "enunciado",
      "kindCode": "E",
      "variant": "regular",
      "variantCode": null,
      "fileName": "P1_IIS_2024_E.pdf",
      "title": "P1 IIS 2024 E"
    },
    {
      "path": "exams/matematica/calculo_diferencial_e_integral/P1_IIS_2024_S.pdf",
      "school": "matematica",
      "subject": "calculo_diferencial_e_integral",
      "year": "2024",
      "semester": "IIS",
      "parcial": "P1",
      "kind": "solution",
      "kindCode": "S",
      "variant": "regular",
      "variantCode": null,
      "fileName": "P1_IIS_2024_S.pdf",
      "title": "P1 IIS 2024 S"
    },
    {
      "path": "exams/matematica/calculo_diferencial_e_integral/P2_IIS_2024_E.pdf",
      "school": "matematica",
      "subject": "calculo_diferencial_e_integral",
      "year": "2024",
      "semester": "IIS",
      "parcial": "P2",
      "kind": "enunciado",
      "kindCode": "E",
      "variant": "regular",
      "variantCode": null,
      "fileName": "P2_IIS_2024_E.pdf",
      "title": "P2 IIS 2024 E"
    },
    {
      "path": "exams/matematica/calculo_diferencial_e_integral/P2_IIS_2024_S.pdf",
      "school": "matematica",
      "subject": "calculo_diferencial_e_integral",
      "year": "2024",
      "semester": "IIS",
      "parcial": "P2",
      "kind": "solution",
      "kindCode": "S",
      "variant": "regular",
      "variantCode": null,
      "fileName": "P2_IIS_2024_S.pdf",
      "title": "P2 IIS 2024 S"
    },
    {
      "path": "exams/matematica/calculo_diferencial_e_integral/P3_IIS_2024_E.pdf",
      "school": "matematica",
      "subject": "calculo_diferencial_e_integral",
      "year": "2024",
      "semester": "IIS",
      "parcial": "P3",
      "kind": "enunciado",
      "kindCode": "E",
      "variant": "regular",
      "variantCode": null,
      "fileName": "P3_IIS_2024_E.pdf",
      "title": "P3 IIS 2024 E"
    },
    {
      "path": "exams/matematica/calculo_diferencial_e_integral/P3_IIS_2024_S.pdf",
      "school": "matematica",
      "subject": "calculo_diferencial_e_integral",
      "year": "2024",
      "semester": "IIS",
      "parcial": "P3",
      "kind": "solution",
      "kindCode": "S",
      "variant": "regular",
      "variantCode": null,
      "fileName": "P3_IIS_2024_S.pdf",
      "title": "P3 IIS 2024 S"
    },
    {
      "path": "exams/matematica/calculo_diferencial_e_integral/RP_IIS_2024_E.pdf",
      "school": "matematica",
      "subject": "calculo_diferencial_e_integral",
      "year": "2024",
      "semester": "IIS",
      "parcial": "RP",
      "kind": "enunciado",
      "kindCode": "E",
      "variant": "regular",
      "variantCode": null,
      "fileName": "RP_IIS_2024_E.pdf",
      "title": "RP IIS 2024 E"
    },
    {
      "path": "exams/matematica/calculo_diferencial_e_integral/RP_IIS_2024_S.pdf",
      "school": "matematica",
      "subject": "calculo_diferencial_e_integral",
      "year": "2024",
      "semester": "IIS",
      "parcial": "RP",
      "kind": "solution",
      "kindCode": "S",
      "variant": "regular",
      "variantCode": null,
      "fileName": "RP_IIS_2024_S.pdf",
      "title": "RP IIS 2024 S"
    },
    {
      "path": "exams/matematica/calculo_diferencial_e_integral/P1_IS_2025_S.pdf",
      "school": "matematica",
      "subject": "calculo_diferencial_e_integral",
      "year": "2025",
      "semester": "IS",
      "parcial": "P1",
      "kind": "solution",
      "kindCode": "S",
      "variant": "regular",
      "variantCode": null,
      "fileName": "P1_IS_2025_S.pdf",
      "title": "P1 IS 2025 S"
    },
    {
      "path": "exams/matematica/calculo_diferencial_e_integral/P2_IS_2025_S.pdf",
      "school": "matematica",
      "subject": "calculo_diferencial_e_integral",
      "year": "2025",
      "semester": "IS",
      "parcial": "P2",
      "kind": "solution",
      "kindCode": "S",
      "variant": "regular",
      "variantCode": null,
      "fileName": "P2_IS_2025_S.pdf",
      "title": "P2 IS 2025 S"
    },
    {
      "path": "exams/matematica/calculo_diferencial_e_integral/P3_IS_2025_S.pdf",
      "school": "matematica",
      "subject": "calculo_diferencial_e_integral",
      "year": "2025",
      "semester": "IS",
      "parcial": "P3",
      "kind": "solution",
      "kindCode": "S",
      "variant": "regular",
      "variantCode": null,
      "fileName": "P3_IS_2025_S.pdf",
      "title": "P3 IS 2025 S"
    },
    {
      "path": "exams/matematica/calculo_y_algebra_lineal/P1_IS_2018_E.pdf",
      "school": "matematica",
      "subject": "calculo_y_algebra_lineal",
      "year": "2018",
      "semester": "IS",
      "parcial": "P1",
      "kind": "enunciado",
      "kindCode": "E",
      "variant": "regular",
      "variantCode": null,
      "fileName": "P1_IS_2018_E.pdf",
      "title": "P1 IS 2018 E"
    },
    {
      "path": "exams/matematica/calculo_y_algebra_lineal/P1_IIS_2018_S_E.pdf",
      "school": "matematica",
      "subject": "calculo_y_algebra_lineal",
      "year": "2018",
      "semester": "IIS",
      "parcial": "P1",
      "kind": "solution",
      "kindCode": "S",
      "variant": "extraordinario",
      "variantCode": "E",
      "fileName": "P1_IIS_2018_S_E.pdf",
      "title": "P1 IIS 2018 S E"
    },
    {
      "path": "exams/matematica/calculo_y_algebra_lineal/P1_IIS_2018_S.pdf",
      "school": "matematica",
      "subject": "calculo_y_algebra_lineal",
      "year": "2018",
      "semester": "IIS",
      "parcial": "P1",
      "kind": "solution",
      "kindCode": "S",
      "variant": "regular",
      "variantCode": null,
      "fileName": "P1_IIS_2018_S.pdf",
      "title": "P1 IIS 2018 S"
    },
    {
      "path": "exams/matematica/calculo_y_algebra_lineal/P1_IIS_2019_E.pdf",
      "school": "matematica",
      "subject": "calculo_y_algebra_lineal",
      "year": "2019",
      "semester": "IIS",
      "parcial": "P1",
      "kind": "enunciado",
      "kindCode": "E",
      "variant": "regular",
      "variantCode": null,
      "fileName": "P1_IIS_2019_E.pdf",
      "title": "P1 IIS 2019 E"
    },
    {
      "path": "exams/matematica/calculo_y_algebra_lineal/P3_IS_2023_E_E.pdf",
      "school": "matematica",
      "subject": "calculo_y_algebra_lineal",
      "year": "2023",
      "semester": "IS",
      "parcial": "P3",
      "kind": "enunciado",
      "kindCode": "E",
      "variant": "extraordinario",
      "variantCode": "E",
      "fileName": "P3_IS_2023_E_E.pdf",
      "title": "P3 IS 2023 E E"
    },
    {
      "path": "exams/matematica/calculo_y_algebra_lineal/P3_IS_2023_S_E.pdf",
      "school": "matematica",
      "subject": "calculo_y_algebra_lineal",
      "year": "2023",
      "semester": "IS",
      "parcial": "P3",
      "kind": "solution",
      "kindCode": "S",
      "variant": "extraordinario",
      "variantCode": "E",
      "fileName": "P3_IS_2023_S_E.pdf",
      "title": "P3 IS 2023 S E"
    },
    {
      "path": "exams/matematica/calculo_y_algebra_lineal/P3_IS_2023_E.pdf",
      "school": "matematica",
      "subject": "calculo_y_algebra_lineal",
      "year": "2023",
      "semester": "IS",
      "parcial": "P3",
      "kind": "enunciado",
      "kindCode": "E",
      "variant": "regular",
      "variantCode": null,
      "fileName": "P3_IS_2023_E.pdf",
      "title": "P3 IS 2023 E"
    },
    {
      "path": "exams/matematica/calculo_y_algebra_lineal/P3_IS_2023_S.pdf",
      "school": "matematica",
      "subject": "calculo_y_algebra_lineal",
      "year": "2023",
      "semester": "IS",
      "parcial": "P3",
      "kind": "solution",
      "kindCode": "S",
      "variant": "regular",
      "variantCode": null,
      "fileName": "P3_IS_2023_S.pdf",
      "title": "P3 IS 2023 S"
    },
    {
      "path": "exams/matematica/calculo_y_algebra_lineal/P3_IIS_2023_S_E.pdf",
      "school": "matematica",
      "subject": "calculo_y_algebra_lineal",
      "year": "2023",
      "semester": "IIS",
      "parcial": "P3",
      "kind": "solution",
      "kindCode": "S",
      "variant": "extraordinario",
      "variantCode": "E",
      "fileName": "P3_IIS_2023_S_E.pdf",
      "title": "P3 IIS 2023 S E"
    },
    {
      "path": "exams/matematica/calculo_y_algebra_lineal/P3_IIS_2023_S.pdf",
      "school": "matematica",
      "subject": "calculo_y_algebra_lineal",
      "year": "2023",
      "semester": "IIS",
      "parcial": "P3",
      "kind": "solution",
      "kindCode": "S",
      "variant": "regular",
      "variantCode": null,
      "fileName": "P3_IIS_2023_S.pdf",
      "title": "P3 IIS 2023 S"
    },
    {
      "path": "exams/matematica/calculo_y_algebra_lineal/P1_IS_2024_S_E.pdf",
      "school": "matematica",
      "subject": "calculo_y_algebra_lineal",
      "year": "2024",
      "semester": "IS",
      "parcial": "P1",
      "kind": "solution",
      "kindCode": "S",
      "variant": "extraordinario",
      "variantCode": "E",
      "fileName": "P1_IS_2024_S_E.pdf",
      "title": "P1 IS 2024 S E"
    },
    {
      "path": "exams/matematica/calculo_y_algebra_lineal/P1_IS_2024_S.pdf",
      "school": "matematica",
      "subject": "calculo_y_algebra_lineal",
      "year": "2024",
      "semester": "IS",
      "parcial": "P1",
      "kind": "solution",
      "kindCode": "S",
      "variant": "regular",
      "variantCode": null,
      "fileName": "P1_IS_2024_S.pdf",
      "title": "P1 IS 2024 S"
    },
    {
      "path": "exams/matematica/calculo_y_algebra_lineal/P1_IIS_2024_E_E.pdf",
      "school": "matematica",
      "subject": "calculo_y_algebra_lineal",
      "year": "2024",
      "semester": "IIS",
      "parcial": "P1",
      "kind": "enunciado",
      "kindCode": "E",
      "variant": "extraordinario",
      "variantCode": "E",
      "fileName": "P1_IIS_2024_E_E.pdf",
      "title": "P1 IIS 2024 E E"
    },
    {
      "path": "exams/matematica/calculo_y_algebra_lineal/P1_IIS_2024_S_E.pdf",
      "school": "matematica",
      "subject": "calculo_y_algebra_lineal",
      "year": "2024",
      "semester": "IIS",
      "parcial": "P1",
      "kind": "solution",
      "kindCode": "S",
      "variant": "extraordinario",
      "variantCode": "E",
      "fileName": "P1_IIS_2024_S_E.pdf",
      "title": "P1 IIS 2024 S E"
    },
    {
      "path": "exams/matematica/calculo_y_algebra_lineal/P1_IIS_2024_E.pdf",
      "school": "matematica",
      "subject": "calculo_y_algebra_lineal",
      "year": "2024",
      "semester": "IIS",
      "parcial": "P1",
      "kind": "enunciado",
      "kindCode": "E",
      "variant": "regular",
      "variantCode": null,
      "fileName": "P1_IIS_2024_E.pdf",
      "title": "P1 IIS 2024 E"
    },
    {
      "path": "exams/matematica/calculo_y_algebra_lineal/P1_IIS_2024_S.pdf",
      "school": "matematica",
      "subject": "calculo_y_algebra_lineal",
      "year": "2024",
      "semester": "IIS",
      "parcial": "P1",
      "kind": "solution",
      "kindCode": "S",
      "variant": "regular",
      "variantCode": null,
      "fileName": "P1_IIS_2024_S.pdf",
      "title": "P1 IIS 2024 S"
    },
    {
      "path": "exams/matematica/calculo_y_algebra_lineal/P1_IS_2025_E_E.pdf",
      "school": "matematica",
      "subject": "calculo_y_algebra_lineal",
      "year": "2025",
      "semester": "IS",
      "parcial": "P1",
      "kind": "enunciado",
      "kindCode": "E",
      "variant": "extraordinario",
      "variantCode": "E",
      "fileName": "P1_IS_2025_E_E.pdf",
      "title": "P1 IS 2025 E E"
    },
    {
      "path": "exams/matematica/calculo_y_algebra_lineal/P1_IS_2025_E.pdf",
      "school": "matematica",
      "subject": "calculo_y_algebra_lineal",
      "year": "2025",
      "semester": "IS",
      "parcial": "P1",
      "kind": "enunciado",
      "kindCode": "E",
      "variant": "regular",
      "variantCode": null,
      "fileName": "P1_IS_2025_E.pdf",
      "title": "P1 IS 2025 E"
    },
    {
      "path": "exams/matematica/calculo_y_algebra_lineal/P2_IS_2025_E_E.pdf",
      "school": "matematica",
      "subject": "calculo_y_algebra_lineal",
      "year": "2025",
      "semester": "IS",
      "parcial": "P2",
      "kind": "enunciado",
      "kindCode": "E",
      "variant": "extraordinario",
      "variantCode": "E",
      "fileName": "P2_IS_2025_E_E.pdf",
      "title": "P2 IS 2025 E E"
    },
    {
      "path": "exams/matematica/calculo_y_algebra_lineal/P2_IS_2025_E.pdf",
      "school": "matematica",
      "subject": "calculo_y_algebra_lineal",
      "year": "2025",
      "semester": "IS",
      "parcial": "P2",
      "kind": "enunciado",
      "kindCode": "E",
      "variant": "regular",
      "variantCode": null,
      "fileName": "P2_IS_2025_E.pdf",
      "title": "P2 IS 2025 E"
    },
    {
      "path": "exams/matematica/matematica_discreta/P3_IIS_2023_S.pdf",
      "school": "matematica",
      "subject": "matematica_discreta",
      "year": "2023",
      "semester": "IIS",
      "parcial": "P3",
      "kind": "solution",
      "kindCode": "S",
      "variant": "regular",
      "variantCode": null,
      "fileName": "P3_IIS_2023_S.pdf",
      "title": "P3 IIS 2023 S"
    },
    {
      "path": "exams/matematica/matematica_discreta/P3_IS_2024_S.pdf",
      "school": "matematica",
      "subject": "matematica_discreta",
      "year": "2024",
      "semester": "IS",
      "parcial": "P3",
      "kind": "solution",
      "kindCode": "S",
      "variant": "regular",
      "variantCode": null,
      "fileName": "P3_IS_2024_S.pdf",
      "title": "P3 IS 2024 S"
    },
    {
      "path": "exams/matematica/matematica_discreta/P3_IIS_2024_S.pdf",
      "school": "matematica",
      "subject": "matematica_discreta",
      "year": "2024",
      "semester": "IIS",
      "parcial": "P3",
      "kind": "solution",
      "kindCode": "S",
      "variant": "regular",
      "variantCode": null,
      "fileName": "P3_IIS_2024_S.pdf",
      "title": "P3 IIS 2024 S"
    },
    {
      "path": "exams/matematica/matematica_general/P1_IS_2024_E.pdf",
      "school": "matematica",
      "subject": "matematica_general",
      "year": "2024",
      "semester": "IS",
      "parcial": "P1",
      "kind": "enunciado",
      "kindCode": "E",
      "variant": "regular",
      "variantCode": null,
      "fileName": "P1_IS_2024_E.pdf",
      "title": "P1 IS 2024 E"
    },
    {
      "path": "exams/matematica/matematica_general/P1_IS_2024_S.pdf",
      "school": "matematica",
      "subject": "matematica_general",
      "year": "2024",
      "semester": "IS",
      "parcial": "P1",
      "kind": "solution",
      "kindCode": "S",
      "variant": "regular",
      "variantCode": null,
      "fileName": "P1_IS_2024_S.pdf",
      "title": "P1 IS 2024 S"
    },
    {
      "path": "exams/matematica/matematica_general/P2_IS_2024_E.pdf",
      "school": "matematica",
      "subject": "matematica_general",
      "year": "2024",
      "semester": "IS",
      "parcial": "P2",
      "kind": "enunciado",
      "kindCode": "E",
      "variant": "regular",
      "variantCode": null,
      "fileName": "P2_IS_2024_E.pdf",
      "title": "P2 IS 2024 E"
    },
    {
      "path": "exams/matematica/matematica_general/P2_IS_2024_S.pdf",
      "school": "matematica",
      "subject": "matematica_general",
      "year": "2024",
      "semester": "IS",
      "parcial": "P2",
      "kind": "solution",
      "kindCode": "S",
      "variant": "regular",
      "variantCode": null,
      "fileName": "P2_IS_2024_S.pdf",
      "title": "P2 IS 2024 S"
    },
    {
      "path": "exams/matematica/matematica_general/P3_IS_2024_E.pdf",
      "school": "matematica",
      "subject": "matematica_general",
      "year": "2024",
      "semester": "IS",
      "parcial": "P3",
      "kind": "enunciado",
      "kindCode": "E",
      "variant": "regular",
      "variantCode": null,
      "fileName": "P3_IS_2024_E.pdf",
      "title": "P3 IS 2024 E"
    },
    {
      "path": "exams/matematica/matematica_general/P3_IS_2024_S.pdf",
      "school": "matematica",
      "subject": "matematica_general",
      "year": "2024",
      "semester": "IS",
      "parcial": "P3",
      "kind": "solution",
      "kindCode": "S",
      "variant": "regular",
      "variantCode": null,
      "fileName": "P3_IS_2024_S.pdf",
      "title": "P3 IS 2024 S"
    },
    {
      "path": "exams/matematica/matematica_general/RP_IS_2024_E.pdf",
      "school": "matematica",
      "subject": "matematica_general",
      "year": "2024",
      "semester": "IS",
      "parcial": "RP",
      "kind": "enunciado",
      "kindCode": "E",
      "variant": "regular",
      "variantCode": null,
      "fileName": "RP_IS_2024_E.pdf",
      "title": "RP IS 2024 E"
    },
    {
      "path": "exams/matematica/matematica_general/RP_IS_2024_S.pdf",
      "school": "matematica",
      "subject": "matematica_general",
      "year": "2024",
      "semester": "IS",
      "parcial": "RP",
      "kind": "solution",
      "kindCode": "S",
      "variant": "regular",
      "variantCode": null,
      "fileName": "RP_IS_2024_S.pdf",
      "title": "RP IS 2024 S"
    },
    {
      "path": "exams/matematica/matematica_general/P1_IIS_2024_E.pdf",
      "school": "matematica",
      "subject": "matematica_general",
      "year": "2024",
      "semester": "IIS",
      "parcial": "P1",
      "kind": "enunciado",
      "kindCode": "E",
      "variant": "regular",
      "variantCode": null,
      "fileName": "P1_IIS_2024_E.pdf",
      "title": "P1 IIS 2024 E"
    },
    {
      "path": "exams/matematica/matematica_general/P1_IIS_2024_S.pdf",
      "school": "matematica",
      "subject": "matematica_general",
      "year": "2024",
      "semester": "IIS",
      "parcial": "P1",
      "kind": "solution",
      "kindCode": "S",
      "variant": "regular",
      "variantCode": null,
      "fileName": "P1_IIS_2024_S.pdf",
      "title": "P1 IIS 2024 S"
    },
    {
      "path": "exams/matematica/matematica_general/P2_IIS_2024_E.pdf",
      "school": "matematica",
      "subject": "matematica_general",
      "year": "2024",
      "semester": "IIS",
      "parcial": "P2",
      "kind": "enunciado",
      "kindCode": "E",
      "variant": "regular",
      "variantCode": null,
      "fileName": "P2_IIS_2024_E.pdf",
      "title": "P2 IIS 2024 E"
    },
    {
      "path": "exams/matematica/matematica_general/P2_IIS_2024_S.pdf",
      "school": "matematica",
      "subject": "matematica_general",
      "year": "2024",
      "semester": "IIS",
      "parcial": "P2",
      "kind": "solution",
      "kindCode": "S",
      "variant": "regular",
      "variantCode": null,
      "fileName": "P2_IIS_2024_S.pdf",
      "title": "P2 IIS 2024 S"
    },
    {
      "path": "exams/matematica/matematica_general/P3_IIS_2024_E.pdf",
      "school": "matematica",
      "subject": "matematica_general",
      "year": "2024",
      "semester": "IIS",
      "parcial": "P3",
      "kind": "enunciado",
      "kindCode": "E",
      "variant": "regular",
      "variantCode": null,
      "fileName": "P3_IIS_2024_E.pdf",
      "title": "P3 IIS 2024 E"
    },
    {
      "path": "exams/matematica/matematica_general/P3_IIS_2024_S.pdf",
      "school": "matematica",
      "subject": "matematica_general",
      "year": "2024",
      "semester": "IIS",
      "parcial": "P3",
      "kind": "solution",
      "kindCode": "S",
      "variant": "regular",
      "variantCode": null,
      "fileName": "P3_IIS_2024_S.pdf",
      "title": "P3 IIS 2024 S"
    },
    {
      "path": "exams/matematica/matematica_general/RP_IIS_2024_E.pdf",
      "school": "matematica",
      "subject": "matematica_general",
      "year": "2024",
      "semester": "IIS",
      "parcial": "RP",
      "kind": "enunciado",
      "kindCode": "E",
      "variant": "regular",
      "variantCode": null,
      "fileName": "RP_IIS_2024_E.pdf",
      "title": "RP IIS 2024 E"
    },
    {
      "path": "exams/matematica/matematica_general/RP_IIS_2024_S.pdf",
      "school": "matematica",
      "subject": "matematica_general",
      "year": "2024",
      "semester": "IIS",
      "parcial": "RP",
      "kind": "solution",
      "kindCode": "S",
      "variant": "regular",
      "variantCode": null,
      "fileName": "RP_IIS_2024_S.pdf",
      "title": "RP IIS 2024 S"
    },
    {
      "path": "exams/matematica/matematica_general/P1_IS_2025_S.pdf",
      "school": "matematica",
      "subject": "matematica_general",
      "year": "2025",
      "semester": "IS",
      "parcial": "P1",
      "kind": "solution",
      "kindCode": "S",
      "variant": "regular",
      "variantCode": null,
      "fileName": "P1_IS_2025_S.pdf",
      "title": "P1 IS 2025 S"
    },
    {
      "path": "exams/matematica/matematica_general/P2_IS_2025_S.pdf",
      "school": "matematica",
      "subject": "matematica_general",
      "year": "2025",
      "semester": "IS",
      "parcial": "P2",
      "kind": "solution",
      "kindCode": "S",
      "variant": "regular",
      "variantCode": null,
      "fileName": "P2_IS_2025_S.pdf",
      "title": "P2 IS 2025 S"
    },
    {
      "path": "exams/matematica/matematica_general/P3_IS_2025_S.pdf",
      "school": "matematica",
      "subject": "matematica_general",
      "year": "2025",
      "semester": "IS",
      "parcial": "P3",
      "kind": "solution",
      "kindCode": "S",
      "variant": "regular",
      "variantCode": null,
      "fileName": "P3_IS_2025_S.pdf",
      "title": "P3 IS 2025 S"
    }
  ]
}
